Workbook

Sheet Net position
A1: Net position — general-platform asset
A2: Every figure derives from Assumptions and Additions. Nothing on this sheet is hardcoded.
A4: Bridge | B4: FTE-months | C4: Cost | D4: vs original
A5: Original committed | B5: =Assumptions!$B$14 -> 178.3 | C5: =Assumptions!$B$15 -> 5093845
A6: less de-duplication against Connect360 | B6: =-Assumptions!$B$20 -> -11.33 | C6: =-Assumptions!$B$21 -> -326330 | D6: =C6/$C$5 -> -0.06406359
A7: plus platform-gap workstreams (A1-A6, A8) | B7: =Additions!$C$28 -> 35 | C7: =Additions!$E$28 -> 821700 | D7: =C7/$C$5 -> 0.16131233
A8: POSITION A — gaps, no worker application | B8: =B5+B6+B7 -> 201.97 | C8: =C5+C6+C7 -> 5589215 | D8: =C8/$C$5-1 -> 0.097248738
A9: plus the worker application (A7) | B9: =Additions!$C$30 -> 33 | C9: =Additions!$E$30 -> 727050 | D9: =C9/$C$5 -> 0.14273108
A10: POSITION B — revised committed total | B10: =B8+B9 -> 234.97 | C10: =C8+C9 -> 6316265 | D10: =C10/$C$5-1 -> 0.23997982
A12: Additions : reductions | C12: =(Additions!$E$28+Additions!$E$30)/Assumptions!$B$21 -> 4.7459627 | D12: The platform credit is ~6% of the build; what the same evidence exposes is ~30%.
A14: DO NOT take '73 weeks released' to a partner as a saving.
A15: It is 73 weeks of SCHEDULE DURATION across parallel rows inside a fixed ~70-week envelope. Converted honestly to effort it is 11.33 FTE-months - 7.4% of the asset build - and it moves no milestone. Foundation Asset GA still lands at wk 24; the programme still ends at wk 70. Neither critical path was touched.
A17: Effect of the v2 re-frame: Position B moved from $6,330,865 to $6,316,265 - a change of $14,600, or 0.2%.
A18: That is not evidence the frame did not matter. It is evidence the estimate was driven by platform evidence rather than by market context, and that v1's error was one of composition and defensibility rather than of total. A geography-specific line in a reusable asset's estimate is indefensible in front of a product review whatever it sums to.

Sheet Assumptions
A1: ACE / WHPC build estimate — validation v2
A2: General-platform frame. Reissued 15 September 2026. Every cost on every sheet derives from B6 and B7.
A4: FRAME
A5: What is being estimated | C5: A general, reusable US health-payer whole-person care platform asset built on IBM Connect360 — hardened and productised for deployment by other teams and for our own multi-tenant SaaS.
A6: What it is NOT | C6: Not a response to any procurement; not a state-specific implementation. v1 of this validation imported a procurement's frame and geography and is superseded.
A7: Source of the frame | C7: The plan's own Assumptions tab: 'a reusable product asset, hardened'; 'configuration-driven and multi-tenant - a new client or state is onboarded in weeks'; 'client implementation ... separate per client - NOT in the asset totals'.
A9: RATE CARD — ILLUSTRATIVE, REPLACE BEFORE ISSUE
A10: Offshore rate ($ / FTE-month) | B10: 14000 | C10: User-supplied plan Assumptions tab. Marked ILLUSTRATIVE in the source workbook.
A11: Onshore rate ($ / FTE-month) | B11: 45000 | C11: User-supplied plan Assumptions tab. Marked ILLUSTRATIVE in the source workbook.
A13: BASELINE (validated to the dollar)
A14: Original committed FTE-months | B14: 178.3 | C14: Plan Cost by Scope: buckets 1+2+3.
A15: Original committed cost | B15: 5093845 | C15: Recomputed from the rate card at the stated per-role offshore shares; ties exactly.
A16: Blended offshore share, as costed | B16: 0.543 | C16: The ACHIEVABLE blend. The plan does NOT cost at the 80% target - costing at target would understate committed scope by $1,492,185 (29.3%).
A18: DE-DUPLICATION CREDIT
A19: Duration weeks released (committed scope) | B19: 73 | C19: DURATION across parallel rows inside a fixed ~70-week envelope. NOT effort. Moves no milestone.
A20: Effort released (FTE-months) | B20: 11.33 | C20: 5.92 offshore / 5.41 onshore. 7.4% of the asset build.
A21: De-duplication credit | B21: 326330 | C21: Recomputed from B6/B7 at 11.33 FTE-mo. Coalition per-line figure was $326,221; the $109 spread is per-line rounding.
A23: Blue = hardcoded input. Black = formula. Yellow = replace before issue.

Sheet Additions
A1: What the Connect360 evidence exposes
A2: Cost = FTE-months x (offshore share x offshore rate + onshore share x onshore rate). Rates live on Assumptions.
A4: Ref | B4: Workstream / role | C4: FTE-months | D4: Offshore share | E4: Cost | F4: Why the plan has no line for it
A5: A1 | B5: Connect360 tenancy & upstream-dependency lane | C5: =SUM(C6:C7) -> 6 | E5: =SUM(E6:E7) -> 204900 | F5: Three things this build needs — a composite citizenEverything resolver, 21 unexposed change subscriptions, and matchPerson/resolveIdentity — sit in another IBM org's backlog.
B6: Solution architect | C6: 3 | D6: 0 | E6: =C6*(D6*Assumptions!$B$10+(1-D6)*Assumptions!$B$11) -> 135000
B7: FHIR / conform engineer | C7: 3 | D7: 0.7 | E7: =C7*(D7*Assumptions!$B$10+(1-D7)*Assumptions!$B$11) -> 69900
A8: A2 | B8: Read-side reporting projection (CQRS) | C8: =SUM(C9:C10) -> 10 | E8: =SUM(E9:E10) -> 195800 | F8: c360-fhir-mp-proxy blocks _total=accurate and _summary=count, so no aggregate is answerable from the FHIR path. Waves 2-5 are full of dashboards. Eight aggregate families plus the platform.
B9: Knowledge-graph engineer | C9: 6 | D9: 0.7 | E9: =C9*(D9*Assumptions!$B$10+(1-D9)*Assumptions!$B$11) -> 139800
B10: Data / integration engineer | C10: 4 | D10: 1 | E10: =C10*(D10*Assumptions!$B$10+(1-D10)*Assumptions!$B$11) -> 56000
A11: A8 | B11: External I&R / CIE federation adapter framework | C11: =SUM(C12:C14) -> 6 | E11: =SUM(E12:E14) -> 142900 | F11: NEW IN v2. In most US markets a commercial closed-loop platform or a 211/AIRS operator already holds the directory and the referral loop. A reusable asset must federate with it. Pluggable framework + two reference adapters (HSDA/Open Referral pull; 360X/Direct push with status round-trip).
B12: FHIR / conform engineer | C12: 3 | D12: 0.7 | E12: =C12*(D12*Assumptions!$B$10+(1-D12)*Assumptions!$B$11) -> 69900
B13: Data / integration engineer | C13: 2 | D13: 1 | E13: =C13*(D13*Assumptions!$B$10+(1-D13)*Assumptions!$B$11) -> 28000
B14: Solution architect | C14: 1 | D14: 0 | E14: =C14*(D14*Assumptions!$B$10+(1-D14)*Assumptions!$B$11) -> 45000
A15: A5 | B15: Directory content-onboarding toolkit (jurisdiction-neutral) | C15: =SUM(C16:C18) -> 5.5 | E15: =SUM(E16:E18) -> 128150 | F15: REPLACES v1 A5 (9.0 FTE-mo / $285,650 for one state's corpus + certified curation operation). The asset ships the LOADER; the CORPUS is per-deployment. Connector framework, AIRS-taxonomy crosswalk, de-duplication, capacity/wait-time population, assurance workflow, curation console.
B16: Social-care / SDOH / CBO SME | C16: 1.5 | D16: 0 | E16: =C16*(D16*Assumptions!$B$10+(1-D16)*Assumptions!$B$11) -> 67500
B17: Data / integration engineer | C17: 3 | D17: 1 | E17: =C17*(D17*Assumptions!$B$10+(1-D17)*Assumptions!$B$11) -> 42000
B18: UX / product designer | C18: 1 | D18: 0.85 | E18: =C18*(D18*Assumptions!$B$10+(1-D18)*Assumptions!$B$11) -> 18650
A19: A3 | B19: Domain-verb mutation workstream (Task) | C19: =SUM(C20:C21) -> 3 | E19: =SUM(E20:E21) -> 63700 | F19: Task mutations are generic CRUD - no acceptReferral / declineReferral(reason) / redirect / requestInformation. The state machine would live in every client and reason codes would drift. Sized 3.0 not 5.0 because the v1 Referral-tracking residual already retains the 7-stage machine.
B20: FHIR / conform engineer | C20: 2 | D20: 0.7 | E20: =C20*(D20*Assumptions!$B$10+(1-D20)*Assumptions!$B$11) -> 46600
B21: Test / conformance & DQ engineer | C21: 1 | D21: 0.9 | E21: =C21*(D21*Assumptions!$B$10+(1-D21)*Assumptions!$B$11) -> 17100
A22: A4 | B22: Consent-enforcement verification + deleteConsent fix | C22: =SUM(C23:C24) -> 2.5 | E22: =SUM(E23:E24) -> 48950 | F22: The consent DATA MODEL is complete; the ENFORCEMENT engine is unproven. deleteConsent destroys the disclosure-accounting trail that survives revocation under 42 CFR Part 2.
B23: Test / conformance & DQ engineer | C23: 1.5 | D23: 0.9 | E23: =C23*(D23*Assumptions!$B$10+(1-D23)*Assumptions!$B$11) -> 25650
B24: FHIR / conform engineer | C24: 1 | D24: 0.7 | E24: =C24*(D24*Assumptions!$B$10+(1-D24)*Assumptions!$B$11) -> 23300
A25: A6 | B25: Profile-binding verification | C25: =SUM(C26:C27) -> 2 | E25: =SUM(E26:E27) -> 37300 | F25: Packages in a repo are not profiles bound in a running server. IG repo carries sdoh_ig_2.0.0, us_core_5.0.1, ibmch v1.0-v1.3 and 18+ SHIN-NY versions on a develop branch 149 commits ahead of main.
B26: Test / conformance & DQ engineer | C26: 1.5 | D26: 0.9 | E26: =C26*(D26*Assumptions!$B$10+(1-D26)*Assumptions!$B$11) -> 25650
B27: FHIR / conform engineer | C27: 0.5 | D27: 0.7 | E27: =C27*(D27*Assumptions!$B$10+(1-D27)*Assumptions!$B$11) -> 11650
B28: SUBTOTAL — platform-gap additions (A1-A6, A8) | C28: =C5+C8+C11+C15+C19+C22+C25 -> 35 | E28: =E5+E8+E11+E15+E19+E22+E25 -> 821700
A30: A7 | B30: Worker / caseworker application — COST EXPOSURE, NOT A SAVING | C30: =SUM(C31:C33) -> 33 | E30: =SUM(E31:E33) -> 727050 | F30: No worker UI exists in Connect360 - only API surface. The staffing model contains NO front-end or application engineering role at all: 4.3 FTE-mo of UX design across 72 weeks and zero build, against ~16 worker-facing surfaces. 112 worker-facing duration weeks remain after de-duplication; at 1.0 concurrent front-end engineer, 112/4.33 = 26.0 FTE-mo. THIS IS THE FLOOR, NOT THE ESTIMATE.
B31: Front-end / application engineer (NEW ROLE — does not exist in the model) | C31: 26 | D31: 0.7 | E31: =C31*(D31*Assumptions!$B$10+(1-D31)*Assumptions!$B$11) -> 605800
B32: UX / product designer (uplift) | C32: 4 | D32: 0.85 | E32: =C32*(D32*Assumptions!$B$10+(1-D32)*Assumptions!$B$11) -> 74600
B33: QA / test engineer (uplift) | C33: 3 | D33: 0.95 | E33: =C33*(D33*Assumptions!$B$10+(1-D33)*Assumptions!$B$11) -> 46650
B35: TOTAL ADDITIONS (A1-A8) | C35: =C28+C30 -> 68 | E35: =E28+E30 -> 1548750
B37: A7 range, stated because the concurrency assumption IS the number: at 1.5 concurrent front-end engineers (prudent for 16 screen families) A7 = 46.0 FTE-mo / $1,029,950.
B38: Carried at the floor so the net position cannot be accused of padding. Tell the partner the number is 33 only if one engineer is genuinely enough.

Sheet Withdrawn in v2
A1: What v1 claimed and v2 withdraws
A2: v1 scored a payer platform asset against a state health-and-human-services procurement and carried that procurement's geography into the estimate.
A4: Ref | B4: v1 item | C4: v1 FTE-mo | D4: v1 cost | E4: Why it is invalid for a platform asset | F4: Replaced by
A5: A5 | B5: State directory corpus + certified curation operation | C5: 9 | D5: 285650 | E5: A named jurisdiction's corpus and its staffed curation run function are PER-DEPLOYMENT CONTENT, not asset build. The asset owes the loader, not the content. | F5: A5' Directory content-onboarding toolkit — 5.5 FTE-mo / $128,150
A6: RT2 | B6: 'The target state already has an incumbent CIE' as a competitive finding | E6: A single market's competitive position is not an input to a reusable asset's cost. The underlying FACT was right and generalises. | F6: A8 External I&R / CIE federation adapter framework — 6.0 FTE-mo / $142,900
A7: — | B7: Tribal / IHS data-sovereignty lane | E7: Geography-specific. | F7: Configurability-is-asserted-never-tested finding (Risks & tests)
A8: — | B8: Programme funding-cycle argument | E8: Geography-specific. | F8: —
A9: — | B9: Every requirement-coverage reference to the CIE procurement | E9: Not the scope being estimated. | F9: —
A10: — | B10: State-specific residual language throughout the de-duplication register | E10: 'state value sets', 'state fixtures', 'state topology', 'state program eligibility' etc. rewritten as configurability residuals. | F10: See De-duplication sheet
A12: WHAT SURVIVES, UNCHANGED AND RE-TESTED UNDER THE CORRECTED FRAME
B13: The arithmetic validation of the model — every bucket, subtotal and per-role split ties to the rate card to the dollar.
B14: All five model defects, chiefly: NO FRONT-END OR APPLICATION ENGINEERING ROLE EXISTS ANYWHERE IN THE PLAN.
B15: The duration-versus-effort correction: 73 weeks is 11.33 FTE-months and moves no milestone.
B16: The de-duplication logic for platform-generic capabilities — 4 C360_WINS, 30 SPLIT, 59 RETAIN, 1 ALREADY_CREDITED.
B17: The worker-application exposure (A7) — a general platform still needs worker UI.
B18: Additions A1, A2, A3, A4 and A6, unchanged.
B19: The EMPI mispricing finding — the largest single mispriced item in the pack.
B20: The rate sensitivity: onshore is 2.85x more sensitive than offshore.

Sheet De-duplication
A1: What Connect360 genuinely removes
A2: 94 phased Gantt rows adjudicated. WksReleased is DURATION, not effort.
A4: Adjudication | B4: Rows | D4: Released by wave | E4: Weeks
A5: C360_WINS | B5: 4 | D5: W0 | E5: 1
A6: SPLIT | B6: 30 | D6: W1 Design+Build | E6: 43
A7: RETAIN | B7: 59 | D7: W1 Secondary | E7: 2
A8: ALREADY_CREDITED | B8: 1 | D8: W2 | E8: 2
A9: TOTAL | B9: =SUM(B5:B8) -> 94 | D9: W3 | E9: 7
D10: W4 | E10: 17
D11: W5 | E11: 1
D12: Client / Improve / Cross-cutting | E12: 0
D13: CMS (optional, outside committed) | E13: 2
D14: Committed-scope total | E14: =SUM(E5:E13)-E13 -> 73
A17: Largest reductions, by effort released | B17: Plan wks | C17: FTE-mo released | D17: Why Connect360 wins
A18: Multi-tenant isolation & tenant onboarding | B18: 13 | C18: 1.2 | D18: /{tenantId}/{resourceType}; proxy asserts URL tenantId matches token; tenant-scoped HSDS schema
A19: Consent & sensitivity labelling at conform | B19: 9 | C19: 0.61 | D19: Full R4 ConsentProvision{securityLabel, purpose, actor, period, action, data, provision(recursive)}
A20: Consent policy governance | B20: 11 | C20: 0.61 | D20: ConsentPolicy{authority, uri}, ConsentVerification, balp_ig_1.1.2 loaded
A21: Integrated data-spine design | B21: 3 | C21: 0.61 | D21: ibmch v1.3, us_core_5.0.1, sdoh_ig_2.0.0 fix the target shape
A22: Referral tracking + journey tracker | B22: 9 | C22: 0.58 | D22: serviceRequestsForOrganization; Task{status, statusReason, businessStatus}
A24: DELIBERATELY NOT REDUCED
A25: Every client-implementation row; security authorisation and pen test; programme governance; CMS conformance testing; every dashboard line (the proxy blocks _total=accurate and _summary=count, so reporting is architecturally thin rather than incidentally missing); every real-time line (one subscription field against 22 change-payload types); the whole agent and knowledge-graph stack; the claims spine; and the four continuous lanes - releasing duration from a lane whose span IS the programme envelope is meaningless.
A27: THE CREDIT IS HELD AT 11.33 FTE-mo, AND THE GENERAL FRAME ARGUES AGAINST IT, NOT FOR IT.
A28: Every retained residual is now a CONFIGURABILITY residual rather than a one-jurisdiction residual: a value-set binding layer for N deployments is not the same size as one state's value sets, and neither is a per-deployment consent-policy authoring surface. Holding the credit constant while the residuals grow is the unfavourable direction for this memo and it is left there deliberately. Sizing the configurability delta is an OPEN ITEM, not a claimed saving.

Sheet Excluded from net
A1: Two costs the asset frame makes visible — both excluded from the net
A2: Excluded because they are conditional or separately staffed. Both will be asked for.
A4: Item | B4: FTE-mo (low) | C4: FTE-mo (high) | D4: Cost (low) | E4: Cost (high) | F4: Basis
A5: Per-deployment implementation unit | B5: 16 | C5: 20 | D5: =B5*37250 -> 596000 | E5: =C5*37250 -> 745000 | F5: The plan is right that client implementation sits outside the asset totals - but a PRODUCT needs a repeatable 'cost to stand up deployment N', and the plan gives it a memo line. The Gantt's own client rows imply it: liaisons wk 10-40, R1 deploy, consent/PHI real-data enablement, EMPI match tuning, security authorisation and pen test, pilot-to-production glide path, at 2-3 concurrent liaisons across ~28 weeks. Costed at a 25% offshore liaison mix. A5's withdrawn $157,500 lands here.
A6: Certification lane (HITRUST r2 / SOC 2 Type II) | B6: 10 | C6: 14 | D6: =B6*40000 -> 400000 | E6: =C6*40000 -> 560000 | F6: No HITRUST, SOC 2, FedRAMP or StateRAMP is evidenced anywhere, and Azure's certifications do not transfer to a solution running on Azure. For a one-off project this is a conditional. FOR A REUSABLE ASSET IT IS STRUCTURAL: the first buyer asks and the answer travels to every subsequent one. Third-party assessor fees sit OUTSIDE this rate card entirely.
A8: Blended rate used: per-deployment $37,250/FTE-mo (25% offshore); certification $40,000/FTE-mo (mostly onshore, internal only).

Sheet Revised roles
A1: Revised per-role model — asset build (buckets 1+2)
A2: Original roles at their stated offshore shares reproduce $4,317,595 and 54.3% offshore EXACTLY. That validation earns the right to the rest.
A4: Role | B4: Original FTE-mo | C4: Released | D4: Added | E4: Revised FTE-mo | F4: Offshore share | G4: Revised cost
A5: Data / integration engineer | B5: 18 | C5: 1.01 | D5: 9 | E5: =B5-C5+D5 -> 25.99 | F5: 1 | G5: =E5*(F5*Assumptions!$B$10+(1-F5)*Assumptions!$B$11) -> 363860
A6: FHIR / conform engineer | B6: 10 | C6: 1.77 | D6: 9.5 | E6: =B6-C6+D6 -> 17.73 | F6: 0.7 | G6: =E6*(F6*Assumptions!$B$10+(1-F6)*Assumptions!$B$11) -> 413109
A7: Knowledge-graph engineer | B7: 10 | C7: 1.09 | D7: 6 | E7: =B7-C7+D7 -> 14.91 | F7: 0.7 | G7: =E7*(F7*Assumptions!$B$10+(1-F7)*Assumptions!$B$11) -> 347403
A8: Intelligence / engine (ML) engineer | B8: 12 | C8: 0.27 | D8: 0 | E8: =B8-C8+D8 -> 11.73 | F8: 0.55 | G8: =E8*(F8*Assumptions!$B$10+(1-F8)*Assumptions!$B$11) -> 327853.5
A9: AI / agent orchestration engineer | B9: 15 | C9: 0.4 | D9: 0 | E9: =B9-C9+D9 -> 14.6 | F9: 0.55 | G9: =E9*(F9*Assumptions!$B$10+(1-F9)*Assumptions!$B$11) -> 408070
A10: Platform / DevSecOps engineer | B10: 12 | C10: 1.22 | D10: 0 | E10: =B10-C10+D10 -> 10.78 | F10: 0.65 | G10: =E10*(F10*Assumptions!$B$10+(1-F10)*Assumptions!$B$11) -> 267883
A11: Terminology / coding specialist | B11: 5 | C11: 0.46 | D11: 0 | E11: =B11-C11+D11 -> 4.54 | F11: 0.45 | G11: =E11*(F11*Assumptions!$B$10+(1-F11)*Assumptions!$B$11) -> 140967
A12: QA / test engineer | B12: 14 | C12: 0.51 | D12: 3 | E12: =B12-C12+D12 -> 16.49 | F12: 0.95 | G12: =E12*(F12*Assumptions!$B$10+(1-F12)*Assumptions!$B$11) -> 256419.5
A13: Test / conformance & DQ engineer | B13: 10 | C13: 0.49 | D13: 4 | E13: =B13-C13+D13 -> 13.51 | F13: 0.9 | G13: =E13*(F13*Assumptions!$B$10+(1-F13)*Assumptions!$B$11) -> 231021
A14: Engagement / programme lead | B14: 15 | C14: 0 | D14: 0 | E14: =B14-C14+D14 -> 15 | F14: 0 | G14: =E14*(F14*Assumptions!$B$10+(1-F14)*Assumptions!$B$11) -> 675000
A15: Solution architect | B15: 13 | C15: 2.16 | D15: 4 | E15: =B15-C15+D15 -> 14.84 | F15: 0 | G15: =E15*(F15*Assumptions!$B$10+(1-F15)*Assumptions!$B$11) -> 667800
A16: UX / product designer | B16: 4.3 | C16: 0.67 | D16: 5 | E16: =B16-C16+D16 -> 8.63 | F16: 0.85 | G16: =E16*(F16*Assumptions!$B$10+(1-F16)*Assumptions!$B$11) -> 160949.5
... A22: Front-end / application engineer (NEW ROLE) | B22: 0 | C22: 0 | D22: 26 | E22: =B22-C22+D22 -> 26 | F22: 0.7 | G22: =E22*(F22*Assumptions!$B$10+(1-F22)*Assumptions!$B$11) -> 605800
A23: ASSET-BUILD TOTAL | B23: =SUM(B5:B22) -> 153.3 | C23: =SUM(C5:C22) -> 11.33 | D23: =SUM(D5:D22) -> 68 | E23: =SUM(E5:E22) -> 209.97 | F23: =SUMPRODUCT(E5:E22,F5:F22)/E23 -> 0.60047864 | G23: =SUM(G5:G22) -> 5540092.5
A25: The revised blended offshore share rises to ~60% from 54.3%, because the additions are engineering-heavy (front-end, knowledge-graph, data/integration, conformance test) and those roles carry offshore shares of 70-100%. It remains below the CORRECTED 72.21% ceiling and well below the 80% target - the structural onshore floor is unchanged and the architect and SME additions are pure onshore.
A27: Reconciliation: this table sums to ~$5,540,092 against a bucket-derived asset build of $5,540,015 - a $77 spread from per-line rounding of the released column (1.01, 1.77, ... vs 11.33 exactly). The Net position sheet uses the bucket-derived figure so that every number follows from the two rate cells.

Sheet Risks & tests
A1: Open risks, and the tests that retire them
A2: None of these was run before '73 weeks released' was claimed. Six are under a day.
A4: # | B4: Test | C4: Effort | D4: What it decides | E4: Exposure
A5: 1 | B5: securityLabel enforcement — write a Consent, query as an out-of-provision principal | C5: 1 hour | D5: Whether Medplum filters provision.securityLabel at QUERY TIME. If it does not, the conform pipeline writes labels nothing enforces - worse than no labelling, because the asset's security documentation will then claim a segmentation it does not deliver, and that claim is carried into EVERY client ATO the asset is handed into. One deployment can discover it; a product propagates it. | E5: +$400k-600k, and reverses 1.22 FTE-mo of credit
A6: 2 | B6: Does the EMPI exist, is it multi-tenant, can it be fronted? | C6: 1 call | D6: The plan budgets 11 weeks to INTEGRATE Connect360's EMPI over PIX/PDQ. There is no $match, no PIX, no PDQ at the gateway, and the EMPI's existence rests on a verbal statement. If absent, single-tenant-bound or unfrontable, identity resolution with survivorship and a stewardship queue lands ON the critical path. Mark RED-UNVERIFIED, not ALREADY_CREDITED. | E6: +$715k-1.0M
A7: 3 | B7: Written commitment from the connect360-saas team on citizenEverything, the 21 unexposed subscriptions and matchPerson, with dates | C7: Ask in writing | D7: Three reductions are booked against another IBM org's unscheduled backlog. The fallback is worse than the schedule risk: polling is blocked by the proxy's count restrictions, and consuming NATS directly BYPASSES c360-fhir-mp-proxy, the sole enforcer of tenant isolation. Under the asset frame this is sharper still - Foundation Asset GA at wk 24 is a promise made to client implementation teams. | E7: Schedule; credit withdrawal
A8: 4 | B8: Is a worker application anywhere in the 36 repos? | C8: Get the repo list | D8: Whether A7 is an exposure or a credit. | E8: $727k
A9: 5 | B9: Are the SDOHCC profiles bound, not just packaged? | C9: Fetch CapabilityStatement, run one $validate | D9: Packages in a repo are not profiles bound in a running server. The develop branch is 149 commits ahead of main. | E9: A6 scope; conformance claims
A10: 6 | B10: Name the two reference external networks the asset ships adapters for, and get their API terms in writing | C10: 1-2 calls | D10: Whether A8 is 6.0 FTE-mo of engineering or a partnership dependency with a named failure mode. | E10: A8 scope; market access
A11: 7 | B11: Has the v8 deck already spent the screening credit? | C11: Read slide 06a | D11: Slide 06a says social/behavioural screening is 'a Connect360 capability we integrate - not built here', which risks crediting the same scope twice. | E11: Double-count
A12: 8 | B12: Stand up a SECOND REFERENCE CONFIGURATION - different payer shape, different value-set pack, different consent posture - and time it | C12: 2-3 weeks | D12: ONLY THE ASSET FRAME ASKS FOR THIS. The Assumptions tab promises 'a new client or state is onboarded in weeks, not re-implemented', and every variable that promise depends on - consent regime, minor-consent age, Part 2 posture, value sets, program eligibility, benefit rules, directory taxonomy, attribution - is a configuration surface with no line, no test and no second reference configuration in the plan. AN ASSET THAT HAS ONLY EVER BEEN CONFIGURED ONCE HAS NOT BEEN PROVEN CONFIGURABLE. | E12: The core product claim
A14: ALSO UNPRICED
B15: Internal chargeback for consuming another IBM P&L's platform - zero dollars in a $5.09M estimate.
B16: Version coupling to a develop branch 149 commits ahead of main.
B17: No costed exit if the Connect360 dependency fails at month nine.
B18: Configurability is asserted and never tested - see test 8.
A20: CONFIDENCE: high on sign, medium-low on magnitude. Additions exceed reductions 4.75x and no plausible parameter reverses that. Swings that matter: worker-app concurrency +/-$303k; consent test failure +$400-600k; certification +$400-560k; EMPI absent +$715k-1.0M; onshore rate +/-20% +/-$754k.
